dmacheck/__init__.py
dmacheck/datadog_utils.py
dmacheck/main.py
dmacheck/opsgenie_utils.py
tests/__init__.py
tests/test_main.py
dmacheck-1.0.6.dist-info/LICENSE
dmacheck-1.0.6.dist-info/METADATA
dmacheck-1.0.6.dist-info/WHEEL
dmacheck-1.0.6.dist-info/entry_points.txt
dmacheck-1.0.6.dist-info/top_level.txt
dmacheck-1.0.6.dist-info/RECORD
