Metadata-Version: 2.1
Name: dmacheck
Version: 1.0.6
Summary: UNKNOWN
Home-page: https://github.com/zackzonexx/dmacheck
Author: Zackzonexx
Author-email: zackzonexx@gmail.com
License: MIT
Project-URL: Source, https://github.com/zackzonexx/dmacheck
Keywords: dmacheck
Platform: UNKNOWN
Classifier: License :: OSI Approved :: MIT License
Classifier: Programming Language :: Python :: 3
Classifier: Operating System :: OS Independent
Classifier: Development Status :: 3 - Alpha
Classifier: Intended Audience :: Developers
Classifier: Topic :: Software Development :: Libraries :: Python Modules
Classifier: Natural Language :: English
Requires-Dist: datadog
Requires-Dist: opsgenie-sdk
Requires-Dist: pytest
Requires-Dist: requests
Requires-Dist: urllib3
